nonebot_plugin_shorturl/__init__.py
nonebot_plugin_shorturl/config.py
nonebot_plugin_shorturl/provider/__init__.py
nonebot_plugin_shorturl/provider/consts.py
nonebot_plugin_shorturl/provider/diskcache.py
nonebot_plugin_shorturl/provider/memory.py
nonebot_plugin_shorturl/provider/redis.py
nonebot_plugin_shorturl-0.4.0.dist-info/LICENSE
nonebot_plugin_shorturl-0.4.0.dist-info/METADATA
nonebot_plugin_shorturl-0.4.0.dist-info/WHEEL
nonebot_plugin_shorturl-0.4.0.dist-info/RECORD
