Metadata-Version: 2.1
Name: nonebot-plugin-shorturl
Version: 0.4.0
Summary: Generate short url by bot for bypassing censorship
Home-page: https://github.com/StarHeartHunt/nonebot-plugin-shorturl
License: MIT
Keywords: nonebot,nonebot2,shorturl
Author: StarHeartHunt
Author-email: starheart233@gmail.com
Requires-Python: >=3.8,<4.0
Classifier: License :: OSI Approved :: MIT License
Classifier: Programming Language :: Python :: 3
Classifier: Programming Language :: Python :: 3.8
Classifier: Programming Language :: Python :: 3.9
Classifier: Programming Language :: Python :: 3.10
Classifier: Programming Language :: Python :: 3.11
Classifier: Programming Language :: Python :: 3.12
Provides-Extra: all
Provides-Extra: diskcache
Provides-Extra: redis
Requires-Dist: diskcache (>=5.6.3,<6.0.0) ; extra == "diskcache" or extra == "all"
Requires-Dist: nonebot2[fastapi] (>=2.0.0,<3.0.0)
Requires-Dist: redis[hiredis] (>=5.0.0,<6.0.0) ; extra == "redis" or extra == "all"
Project-URL: Documentation, https://github.com/StarHeartHunt/nonebot-plugin-shorturl#readme
Project-URL: Repository, https://github.com/StarHeartHunt/nonebot-plugin-shorturl
